AUTHORS
LICENSE
MANIFEST.in
compareQual.pyx
setup.cfg
setup.py
bin/fmrc
fmrc/__init__.py
fmrc/correct.c
fmrc/correct.pyx
fmrc/crctErrs.py
fmrc/rnaCrct.py
fmrc/util.py
fmrc.egg-info/PKG-INFO
fmrc.egg-info/SOURCES.txt
fmrc.egg-info/dependency_links.txt
fmrc.egg-info/not-zip-safe
fmrc.egg-info/requires.txt
fmrc.egg-info/top_level.txt