Metadata-Version: 1.0
Name: fmrc
Version: 0.0.4
Summary: Corrects errors in short reads from high-throughput sequencing
Home-page: http://github.com/sgreenstein/fmrc
Author: Seth Greenstein
Author-email: sgreens@cs.unc.edu
License: MIT
Platform: UNKNOWN
